CHANGES.rst
COPYING
COPYING.LESSER
MANIFEST.in
Makefile
README.rst
buildout.cfg
ez_setup.py
requirements.in
requirements.txt
setup.cfg
setup.py
tox.ini
requirements/dev.in
requirements/dev.txt
requirements/docs.in
requirements/docs.txt
requirements/lint.in
requirements/lint.txt
requirements/site.in
requirements/site.txt
requirements/test.in
requirements/test.txt
src/mete0r/__init__.py
src/mete0r.recipe.whoami.egg-info/PKG-INFO
src/mete0r.recipe.whoami.egg-info/SOURCES.txt
src/mete0r.recipe.whoami.egg-info/dependency_links.txt
src/mete0r.recipe.whoami.egg-info/entry_points.txt
src/mete0r.recipe.whoami.egg-info/namespace_packages.txt
src/mete0r.recipe.whoami.egg-info/requires.txt
src/mete0r.recipe.whoami.egg-info/top_level.txt
src/mete0r.recipe.whoami.egg-info/zip-safe
src/mete0r/recipe/__init__.py
src/mete0r/recipe/whoami/__init__.py