Metadata-Version: 2.1
Name: mete0r.recipe.whoami
Version: 0.1.2
Summary: a zc.buildout recipe to know whoami
Home-page: https://github.com/mete0r/recipe.whoami
Author: mete0r
Author-email: mete0r@sarangbang.or.kr
License: GNU Lesser General Public License v3 or later (LGPLv3+)
Keywords: zc.buildout,recipe,whoami
Platform: UNKNOWN
Classifier: Development Status :: 3 - Alpha
Classifier: Environment :: Plugins
Classifier: Framework :: Buildout :: Recipe
Classifier: Intended Audience :: Developers
Classifier: License :: OSI Approved :: GNU Lesser General Public License v3 or later (LGPLv3+)
Classifier: Operating System :: POSIX :: Linux
Classifier: Programming Language :: Python :: 2.7
Classifier: Programming Language :: Python :: Implementation :: CPython
Provides-Extra: test
